DAINodeWidgets.py
DAINodes.py
DAIPipelineGraph.py
EveryNode.json
ExampleGraph.json
MANIFEST.in
README.md
demo.py
install_requirements.py
pipeline_editor.py
requirements.txt
NodeGraphQt/__init__.py
NodeGraphQt/constants.py
NodeGraphQt/errors.py
NodeGraphQt/pkg_info.py
NodeGraphQt/base/__init__.py
NodeGraphQt/base/commands.py
NodeGraphQt/base/factory.py
NodeGraphQt/base/graph.py
NodeGraphQt/base/menu.py
NodeGraphQt/base/model.py
NodeGraphQt/base/node.py
NodeGraphQt/base/port.py
NodeGraphQt/base/utils.py
NodeGraphQt/qgraphics/__init__.py
NodeGraphQt/qgraphics/node_abstract.py
NodeGraphQt/qgraphics/node_backdrop.py
NodeGraphQt/qgraphics/node_base.py
NodeGraphQt/qgraphics/node_overlay_disabled.py
NodeGraphQt/qgraphics/node_text_item.py
NodeGraphQt/qgraphics/pipe.py
NodeGraphQt/qgraphics/port.py
NodeGraphQt/qgraphics/slicer.py
NodeGraphQt/widgets/__init__.py
NodeGraphQt/widgets/actions.py
NodeGraphQt/widgets/dialogs.py
NodeGraphQt/widgets/node_publish_widget.py
NodeGraphQt/widgets/node_space_bar.py
NodeGraphQt/widgets/node_widgets.py
NodeGraphQt/widgets/nodes_palette.py
NodeGraphQt/widgets/nodes_tree.py
NodeGraphQt/widgets/properties.py
NodeGraphQt/widgets/properties_bin.py
NodeGraphQt/widgets/scene.py
NodeGraphQt/widgets/stylesheet.py
NodeGraphQt/widgets/tab_search.py
NodeGraphQt/widgets/viewer.py
NodeGraphQt/widgets/icons/down_arrow.png
NodeGraphQt/widgets/icons/node_base.png
depthai_gui.egg-info/PKG-INFO
depthai_gui.egg-info/SOURCES.txt
depthai_gui.egg-info/dependency_links.txt
depthai_gui.egg-info/entry_points.txt
depthai_gui.egg-info/requires.txt
depthai_gui.egg-info/top_level.txt
depthai_gui-2.0.6.dist-info/METADATA
depthai_gui-2.0.6.dist-info/WHEEL
depthai_gui-2.0.6.dist-info/entry_points.txt
depthai_gui-2.0.6.dist-info/top_level.txt
depthai_gui-2.0.6.dist-info/RECORD
