Metadata-Version: 2.1
Name: depthai-gui
Version: 2.0.6
Summary: DepthAI Pipeline Visualizer GUI
Home-page: https://github.com/luxonis/depthai-gui
Author: Luxonis
Author-email: support@luxonis.com
License: UNKNOWN
Project-URL: Bug Tracker, https://github.com/luxonis/depthai-gui/issues
Project-URL: Documentation, https://docs.luxonis.com/projects/gui/en/latest/
Project-URL: Source Code, https://github.com/luxonis/depthai-gui
Keywords: depthai gui ide pipeline visualizer node
Platform: UNKNOWN
Classifier: License :: OSI Approved :: Apache Software License
Classifier: Programming Language :: Python
Classifier: Programming Language :: Python :: 3
Classifier: Programming Language :: Python :: 3.6
Classifier: Programming Language :: Python :: 3.7
Classifier: Programming Language :: Python :: 3.8
Classifier: Programming Language :: Python :: 3.9
Requires-Dist: opencv-python
Requires-Dist: depthai (==2.13.3.0)
Requires-Dist: pyqt5
Requires-Dist: Qt.py
Requires-Dist: pathlib
